__init__.py
riptide.py
riptide-3.4.81.dist-info/LICENSE.txt
riptide-3.4.81.dist-info/METADATA
riptide-3.4.81.dist-info/WHEEL
riptide-3.4.81.dist-info/top_level.txt
riptide-3.4.81.dist-info/RECORD
