Metadata-Version: 2.1
Name: riptide
Version: 3.4.81
Summary: Reaction Inclusion by Parsimony and Transcript Distribution (RIPTiDe)
Author-email: Matthew Jenior <mattjenior@gmail.com>
Project-URL: Homepage, https://github.com/mjenior/riptide
Project-URL: Bug Tracker, https://github.com/mjenior/riptide/issues
Classifier: Programming Language :: Python :: 3
Classifier: License :: OSI Approved :: MIT License
Classifier: Operating System :: OS Independent
Requires-Python: >=3.6
License-File: LICENSE.txt
